pyjsonutils/__init__.py
pyjsonutils/main.py
pyjsonutils/pyjsonutils.py
pyjsonutils-0.3.0.dist-info/LICENSE
pyjsonutils-0.3.0.dist-info/METADATA
pyjsonutils-0.3.0.dist-info/WHEEL
pyjsonutils-0.3.0.dist-info/top_level.txt
pyjsonutils-0.3.0.dist-info/RECORD
